<annotation><folder>VOC2007</folder><filename>CARDS_LIVINGROOM_T_B_frame_1424.jpg</filename><size><width>1280</width><height>720</height><depth>3</depth></size><segmented>0</segmented><object><name>hand</name><pose>Unspecified</pose><truncated>0</truncated><difficult>0</difficult><bndbox><xmin>753</xmin><ymin>285</ymin><xmax>1006</xmax><ymax>446</ymax></bndbox></object><object><name>hand</name><pose>Unspecified</pose><truncated>0</truncated><difficult>0</difficult><bndbox><xmin>472</xmin><ymin>299</ymin><xmax>685</xmax><ymax>462</ymax></bndbox></object></annotation>