<annotation><folder>VOC2007</folder><filename>CARDS_OFFICE_T_H_frame_1693.jpg</filename><size><width>1280</width><height>720</height><depth>3</depth></size><segmented>0</segmented><object><name>hand</name><pose>Unspecified</pose><truncated>0</truncated><difficult>0</difficult><bndbox><xmin>207</xmin><ymin>607</ymin><xmax>399</xmax><ymax>719</ymax></bndbox></object><object><name>hand</name><pose>Unspecified</pose><truncated>0</truncated><difficult>0</difficult><bndbox><xmin>522</xmin><ymin>543</ymin><xmax>789</xmax><ymax>719</ymax></bndbox></object><object><name>hand</name><pose>Unspecified</pose><truncated>0</truncated><difficult>0</difficult><bndbox><xmin>573</xmin><ymin>130</ymin><xmax>726</xmax><ymax>215</ymax></bndbox></object><object><name>hand</name><pose>Unspecified</pose><truncated>0</truncated><difficult>0</difficult><bndbox><xmin>357</xmin><ymin>5</ymin><xmax>455</xmax><ymax>88</ymax></bndbox></object></annotation>