<annotation><folder>VOC2007</folder><filename>CARDS_LIVINGROOM_T_B_frame_0898.jpg</filename><size><width>1280</width><height>720</height><depth>3</depth></size><segmented>0</segmented><object><name>hand</name><pose>Unspecified</pose><truncated>0</truncated><difficult>0</difficult><bndbox><xmin>745</xmin><ymin>344</ymin><xmax>965</xmax><ymax>484</ymax></bndbox></object><object><name>hand</name><pose>Unspecified</pose><truncated>0</truncated><difficult>0</difficult><bndbox><xmin>506</xmin><ymin>312</ymin><xmax>706</xmax><ymax>475</ymax></bndbox></object></annotation>