<annotation><folder>VOC2007</folder><filename>CARDS_LIVINGROOM_H_S_frame_0160.jpg</filename><size><width>1280</width><height>720</height><depth>3</depth></size><segmented>0</segmented><object><name>hand</name><pose>Unspecified</pose><truncated>0</truncated><difficult>0</difficult><bndbox><xmin>699</xmin><ymin>560</ymin><xmax>1027</xmax><ymax>716</ymax></bndbox></object><object><name>hand</name><pose>Unspecified</pose><truncated>0</truncated><difficult>0</difficult><bndbox><xmin>656</xmin><ymin>317</ymin><xmax>819</xmax><ymax>427</ymax></bndbox></object><object><name>hand</name><pose>Unspecified</pose><truncated>0</truncated><difficult>0</difficult><bndbox><xmin>371</xmin><ymin>187</ymin><xmax>521</xmax><ymax>318</ymax></bndbox></object></annotation>