<annotation><folder>VOC2007</folder><filename>CHESS_OFFICE_T_H_frame_1656.jpg</filename><size><width>1280</width><height>720</height><depth>3</depth></size><segmented>0</segmented><object><name>hand</name><pose>Unspecified</pose><truncated>0</truncated><difficult>0</difficult><bndbox><xmin>43</xmin><ymin>293</ymin><xmax>432</xmax><ymax>490</ymax></bndbox></object><object><name>hand</name><pose>Unspecified</pose><truncated>0</truncated><difficult>0</difficult><bndbox><xmin>505</xmin><ymin>618</ymin><xmax>766</xmax><ymax>718</ymax></bndbox></object><object><name>hand</name><pose>Unspecified</pose><truncated>0</truncated><difficult>0</difficult><bndbox><xmin>583</xmin><ymin>76</ymin><xmax>722</xmax><ymax>176</ymax></bndbox></object><object><name>hand</name><pose>Unspecified</pose><truncated>0</truncated><difficult>0</difficult><bndbox><xmin>402</xmin><ymin>156</ymin><xmax>550</xmax><ymax>254</ymax></bndbox></object></annotation>