<annotation><folder>VOC2007</folder><filename>JENGA_LIVINGROOM_H_B_frame_0515.jpg</filename><size><width>1280</width><height>720</height><depth>3</depth></size><segmented>0</segmented><object><name>hand</name><pose>Unspecified</pose><truncated>0</truncated><difficult>0</difficult><bndbox><xmin>670</xmin><ymin>552</ymin><xmax>1023</xmax><ymax>718</ymax></bndbox></object><object><name>hand</name><pose>Unspecified</pose><truncated>0</truncated><difficult>0</difficult><bndbox><xmin>716</xmin><ymin>411</ymin><xmax>911</xmax><ymax>551</ymax></bndbox></object><object><name>hand</name><pose>Unspecified</pose><truncated>0</truncated><difficult>0</difficult><bndbox><xmin>191</xmin><ymin>384</ymin><xmax>371</xmax><ymax>564</ymax></bndbox></object></annotation>