<annotation><folder>VOC2007</folder><filename>JENGA_COURTYARD_B_H_frame_2568.jpg</filename><size><width>1280</width><height>720</height><depth>3</depth></size><segmented>0</segmented><object><name>hand</name><pose>Unspecified</pose><truncated>0</truncated><difficult>0</difficult><bndbox><xmin>310</xmin><ymin>652</ymin><xmax>441</xmax><ymax>719</ymax></bndbox></object><object><name>hand</name><pose>Unspecified</pose><truncated>0</truncated><difficult>0</difficult><bndbox><xmin>661</xmin><ymin>399</ymin><xmax>771</xmax><ymax>529</ymax></bndbox></object><object><name>hand</name><pose>Unspecified</pose><truncated>0</truncated><difficult>0</difficult><bndbox><xmin>347</xmin><ymin>138</ymin><xmax>520</xmax><ymax>323</ymax></bndbox></object></annotation>