<annotation><folder>VOC2007</folder><filename>PUZZLE_COURTYARD_B_S_frame_1662.jpg</filename><size><width>1280</width><height>720</height><depth>3</depth></size><segmented>0</segmented><object><name>hand</name><pose>Unspecified</pose><truncated>0</truncated><difficult>0</difficult><bndbox><xmin>323</xmin><ymin>587</ymin><xmax>485</xmax><ymax>719</ymax></bndbox></object><object><name>hand</name><pose>Unspecified</pose><truncated>0</truncated><difficult>0</difficult><bndbox><xmin>542</xmin><ymin>435</ymin><xmax>756</xmax><ymax>615</ymax></bndbox></object><object><name>hand</name><pose>Unspecified</pose><truncated>0</truncated><difficult>0</difficult><bndbox><xmin>735</xmin><ymin>452</ymin><xmax>968</xmax><ymax>641</ymax></bndbox></object><object><name>hand</name><pose>Unspecified</pose><truncated>0</truncated><difficult>0</difficult><bndbox><xmin>354</xmin><ymin>297</ymin><xmax>527</xmax><ymax>492</ymax></bndbox></object></annotation>