<annotation><folder>VOC2007</folder><filename>PUZZLE_LIVINGROOM_T_B_frame_0141.jpg</filename><size><width>1280</width><height>720</height><depth>3</depth></size><segmented>0</segmented><object><name>hand</name><pose>Unspecified</pose><truncated>0</truncated><difficult>0</difficult><bndbox><xmin>6</xmin><ymin>383</ymin><xmax>208</xmax><ymax>614</ymax></bndbox></object><object><name>hand</name><pose>Unspecified</pose><truncated>0</truncated><difficult>0</difficult><bndbox><xmin>700</xmin><ymin>606</ymin><xmax>1232</xmax><ymax>718</ymax></bndbox></object><object><name>hand</name><pose>Unspecified</pose><truncated>0</truncated><difficult>0</difficult><bndbox><xmin>784</xmin><ymin>147</ymin><xmax>1072</xmax><ymax>311</ymax></bndbox></object><object><name>hand</name><pose>Unspecified</pose><truncated>0</truncated><difficult>0</difficult><bndbox><xmin>501</xmin><ymin>99</ymin><xmax>691</xmax><ymax>252</ymax></bndbox></object></annotation>