<annotation><folder>VOC2007</folder><filename>PUZZLE_LIVINGROOM_S_H_frame_2129.jpg</filename><size><width>1280</width><height>720</height><depth>3</depth></size><segmented>0</segmented><object><name>hand</name><pose>Unspecified</pose><truncated>0</truncated><difficult>0</difficult><bndbox><xmin>601</xmin><ymin>633</ymin><xmax>925</xmax><ymax>718</ymax></bndbox></object><object><name>hand</name><pose>Unspecified</pose><truncated>0</truncated><difficult>0</difficult><bndbox><xmin>823</xmin><ymin>161</ymin><xmax>1025</xmax><ymax>309</ymax></bndbox></object><object><name>hand</name><pose>Unspecified</pose><truncated>0</truncated><difficult>0</difficult><bndbox><xmin>457</xmin><ymin>182</ymin><xmax>647</xmax><ymax>335</ymax></bndbox></object></annotation>