<annotation><folder>VOC2007</folder><filename>PUZZLE_OFFICE_H_B_frame_0505.jpg</filename><size><width>1280</width><height>720</height><depth>3</depth></size><segmented>0</segmented><object><name>hand</name><pose>Unspecified</pose><truncated>0</truncated><difficult>0</difficult><bndbox><xmin>137</xmin><ymin>666</ymin><xmax>352</xmax><ymax>716</ymax></bndbox></object><object><name>hand</name><pose>Unspecified</pose><truncated>0</truncated><difficult>0</difficult><bndbox><xmin>710</xmin><ymin>370</ymin><xmax>1049</xmax><ymax>643</ymax></bndbox></object><object><name>hand</name><pose>Unspecified</pose><truncated>0</truncated><difficult>0</difficult><bndbox><xmin>678</xmin><ymin>231</ymin><xmax>846</xmax><ymax>396</ymax></bndbox></object><object><name>hand</name><pose>Unspecified</pose><truncated>0</truncated><difficult>0</difficult><bndbox><xmin>243</xmin><ymin>296</ymin><xmax>405</xmax><ymax>500</ymax></bndbox></object></annotation>