<annotation><folder>VOC2007</folder><filename>PUZZLE_OFFICE_H_B_frame_1881.jpg</filename><size><width>1280</width><height>720</height><depth>3</depth></size><segmented>0</segmented><object><name>hand</name><pose>Unspecified</pose><truncated>0</truncated><difficult>0</difficult><bndbox><xmin>363</xmin><ymin>549</ymin><xmax>623</xmax><ymax>717</ymax></bndbox></object><object><name>hand</name><pose>Unspecified</pose><truncated>0</truncated><difficult>0</difficult><bndbox><xmin>739</xmin><ymin>464</ymin><xmax>948</xmax><ymax>640</ymax></bndbox></object><object><name>hand</name><pose>Unspecified</pose><truncated>0</truncated><difficult>0</difficult><bndbox><xmin>532</xmin><ymin>245</ymin><xmax>719</xmax><ymax>422</ymax></bndbox></object><object><name>hand</name><pose>Unspecified</pose><truncated>0</truncated><difficult>0</difficult><bndbox><xmin>311</xmin><ymin>264</ymin><xmax>455</xmax><ymax>422</ymax></bndbox></object></annotation>