<annotation><folder>VOC2007</folder><filename>PUZZLE_LIVINGROOM_B_T_frame_0227.jpg</filename><size><width>1280</width><height>720</height><depth>3</depth></size><segmented>0</segmented><object><name>hand</name><pose>Unspecified</pose><truncated>0</truncated><difficult>0</difficult><bndbox><xmin>878</xmin><ymin>653</ymin><xmax>1176</xmax><ymax>716</ymax></bndbox></object><object><name>hand</name><pose>Unspecified</pose><truncated>0</truncated><difficult>0</difficult><bndbox><xmin>438</xmin><ymin>266</ymin><xmax>634</xmax><ymax>397</ymax></bndbox></object><object><name>hand</name><pose>Unspecified</pose><truncated>0</truncated><difficult>0</difficult><bndbox><xmin>101</xmin><ymin>244</ymin><xmax>338</xmax><ymax>404</ymax></bndbox></object></annotation>