<annotation><folder>VOC2007</folder><filename>PUZZLE_OFFICE_T_S_frame_1694.jpg</filename><size><width>1280</width><height>720</height><depth>3</depth></size><segmented>0</segmented><object><name>hand</name><pose>Unspecified</pose><truncated>0</truncated><difficult>0</difficult><bndbox><xmin>96</xmin><ymin>273</ymin><xmax>457</xmax><ymax>546</ymax></bndbox></object><object><name>hand</name><pose>Unspecified</pose><truncated>0</truncated><difficult>0</difficult><bndbox><xmin>606</xmin><ymin>344</ymin><xmax>849</xmax><ymax>655</ymax></bndbox></object><object><name>hand</name><pose>Unspecified</pose><truncated>0</truncated><difficult>0</difficult><bndbox><xmin>970</xmin><ymin>458</ymin><xmax>1270</xmax><ymax>715</ymax></bndbox></object><object><name>hand</name><pose>Unspecified</pose><truncated>0</truncated><difficult>0</difficult><bndbox><xmin>226</xmin><ymin>7</ymin><xmax>452</xmax><ymax>121</ymax></bndbox></object></annotation>